{
    "key": "group_5dc150fb8fe71",
    "title": "Tekst rotator",
    "fields": [
        {
            "key": "field_5dc15120776fd",
            "label": "Overskrift",
            "name": "rotator_title",
            "type": "text",
            "instructions": "",
            "required": 0,
            "conditional_logic": 0,
            "wrapper": {
                "width": "",
                "class": "",
                "id": ""
            },
            "default_value": "",
            "placeholder": "",
            "prepend": "",
            "append": "",
            "maxlength": ""
        },
        {
            "key": "field_5dc15128776fe",
            "label": "Roterende ord",
            "name": "rotator_words",
            "type": "repeater",
            "instructions": "",
            "required": 0,
            "conditional_logic": 0,
            "wrapper": {
                "width": "",
                "class": "",
                "id": ""
            },
            "collapsed": "",
            "min": 0,
            "max": 0,
            "layout": "table",
            "button_label": "Tilføj ord",
            "sub_fields": [
                {
                    "key": "field_5dc1513a776ff",
                    "label": "Ord",
                    "name": "word",
                    "type": "text",
                    "instructions": "",
                    "required": 0,
                    "conditional_logic": 0,
                    "wrapper": {
                        "width": "",
                        "class": "",
                        "id": ""
                    },
                    "default_value": "",
                    "placeholder": "",
                    "prepend": "",
                    "append": "",
                    "maxlength": ""
                }
            ]
        },
        {
            "key": "field_5dc1515c77700",
            "label": "Ekstra tekst",
            "name": "rotator_content",
            "type": "wysiwyg",
            "instructions": "",
            "required": 0,
            "conditional_logic": 0,
            "wrapper": {
                "width": "",
                "class": "",
                "id": ""
            },
            "default_value": "",
            "tabs": "text",
            "media_upload": 1,
            "toolbar": "full",
            "delay": 0
        }
    ],
    "location": [
        [
            {
                "param": "post_template",
                "operator": "==",
                "value": "views\/template-frontpage.blade.php"
            }
        ]
    ],
    "menu_order": 0,
    "position": "normal",
    "style": "default",
    "label_placement": "top",
    "instruction_placement": "label",
    "hide_on_screen": "",
    "active": 1,
    "description": "",
    "modified": 1572950992
}